nrc_exporter.py
nrc_exporter-0.0.7.dist-info/LICENSE
nrc_exporter-0.0.7.dist-info/METADATA
nrc_exporter-0.0.7.dist-info/WHEEL
nrc_exporter-0.0.7.dist-info/entry_points.txt
nrc_exporter-0.0.7.dist-info/top_level.txt
nrc_exporter-0.0.7.dist-info/RECORD
