Metadata-Version: 2.1
Name: nrc-exporter
Version: 0.0.7
Summary: This program allows you to export your runs from Nike Run Club and convert them to GPX format
Home-page: https://github.com/yasoob/nrc-exporter
Author: Yasoob Khalid
Author-email: hi@yasoob.me
License: UNKNOWN
Platform: UNKNOWN
Classifier: Programming Language :: Python :: 3
Classifier: Programming Language :: Python :: 3.4
Classifier: Programming Language :: Python :: 3.7
Classifier: Programming Language :: Python :: 3.8
Classifier: Programming Language :: Python :: Implementation :: CPython
Classifier: License :: OSI Approved :: MIT License
Classifier: Operating System :: OS Independent
Requires-Python: >=3.4
Requires-Dist: colorama (==0.4.3)
Requires-Dist: gpxpy (==1.4.2)
Requires-Dist: requests (==2.24.0)
Requires-Dist: selenium (==3.141.0)
Requires-Dist: selenium-wire (==1.2.3)
